aacgmv2/__init__.py
aacgmv2/__main__.py
aacgmv2/_aacgmv2.cpython-310-darwin.so
aacgmv2/aacgmv2module.c
aacgmv2/igrf14coeffs.txt
aacgmv2/magmodel_1590-2025.txt
aacgmv2/utils.py
aacgmv2/wrapper.py
aacgmv2/aacgm_coeffs/aacgm_coeffs-14-1590.asc
aacgmv2/aacgm_coeffs/aacgm_coeffs-14-1595.asc
aacgmv2/aacgm_coeffs/aacgm_coeffs-14-1600.asc
aacgmv2/aacgm_coeffs/aacgm_coeffs-14-1605.asc
aacgmv2/aacgm_coeffs/aacgm_coeffs-14-1610.asc
aacgmv2/aacgm_coeffs/aacgm_coeffs-14-1615.asc
aacgmv2/aacgm_coeffs/aacgm_coeffs-14-1620.asc
aacgmv2/aacgm_coeffs/aacgm_coeffs-14-1625.asc
aacgmv2/aacgm_coeffs/aacgm_coeffs-14-1630.asc
aacgmv2/aacgm_coeffs/aacgm_coeffs-14-1635.asc
aacgmv2/aacgm_coeffs/aacgm_coeffs-14-1640.asc
aacgmv2/aacgm_coeffs/aacgm_coeffs-14-1645.asc
aacgmv2/aacgm_coeffs/aacgm_coeffs-14-1650.asc
aacgmv2/aacgm_coeffs/aacgm_coeffs-14-1655.asc
aacgmv2/aacgm_coeffs/aacgm_coeffs-14-1660.asc
aacgmv2/aacgm_coeffs/aacgm_coeffs-14-1665.asc
aacgmv2/aacgm_coeffs/aacgm_coeffs-14-1670.asc
aacgmv2/aacgm_coeffs/aacgm_coeffs-14-1675.asc
aacgmv2/aacgm_coeffs/aacgm_coeffs-14-1680.asc
aacgmv2/aacgm_coeffs/aacgm_coeffs-14-1685.asc
aacgmv2/aacgm_coeffs/aacgm_coeffs-14-1690.asc
aacgmv2/aacgm_coeffs/aacgm_coeffs-14-1695.asc
aacgmv2/aacgm_coeffs/aacgm_coeffs-14-1700.asc
aacgmv2/aacgm_coeffs/aacgm_coeffs-14-1705.asc
aacgmv2/aacgm_coeffs/aacgm_coeffs-14-1710.asc
aacgmv2/aacgm_coeffs/aacgm_coeffs-14-1715.asc
aacgmv2/aacgm_coeffs/aacgm_coeffs-14-1720.asc
aacgmv2/aacgm_coeffs/aacgm_coeffs-14-1725.asc
aacgmv2/aacgm_coeffs/aacgm_coeffs-14-1730.asc
aacgmv2/aacgm_coeffs/aacgm_coeffs-14-1735.asc
aacgmv2/aacgm_coeffs/aacgm_coeffs-14-1740.asc
aacgmv2/aacgm_coeffs/aacgm_coeffs-14-1745.asc
aacgmv2/aacgm_coeffs/aacgm_coeffs-14-1750.asc
aacgmv2/aacgm_coeffs/aacgm_coeffs-14-1755.asc
aacgmv2/aacgm_coeffs/aacgm_coeffs-14-1760.asc
aacgmv2/aacgm_coeffs/aacgm_coeffs-14-1765.asc
aacgmv2/aacgm_coeffs/aacgm_coeffs-14-1770.asc
aacgmv2/aacgm_coeffs/aacgm_coeffs-14-1775.asc
aacgmv2/aacgm_coeffs/aacgm_coeffs-14-1780.asc
aacgmv2-2.7.0.dist-info/AUTHORS.rst
aacgmv2-2.7.0.dist-info/LICENSE
aacgmv2-2.7.0.dist-info/LICENSE-AstAlg.txt
aacgmv2-2.7.0.dist-info/METADATA
aacgmv2-2.7.0.dist-info/WHEEL
aacgmv2-2.7.0.dist-info/entry_points.txt
aacgmv2-2.7.0.dist-info/top_level.txt
aacgmv2-2.7.0.dist-info/RECORD
