Metadata-Version: 2.1
Name: aacgmv2
Version: 2.7.0
Summary: A Python wrapper for AACGM-v2 magnetic coordinates
Maintainer-email: "Angeline G. Burrell" <angeline.g.burrell.civ@us.navy.mil>
License: The MIT License (MIT)
Project-URL: source, https://github.com/aburrell/aacgmv2
Project-URL: documentation, https://aacgmv2.readthedocs.io/en/latest/
Project-URL: tracker, https://github.com/aburrell/aacgmv2/issues
Project-URL: download, https://github.com/aburrell/aacgmv2/releases
Keywords: aacgm,aacgm-v2,aacgmv2,magnetic coordinates,altitude adjusted corrected geomagnetic coordinates,mlt,magnetic local time,conversion,converting
Classifier: Development Status :: 5 - Production/Stable
Classifier: Intended Audience :: Science/Research
Classifier: License :: OSI Approved :: MIT License
Classifier: Operating System :: Unix
Classifier: Operating System :: POSIX
Classifier: Operating System :: MacOS :: MacOS X
Classifier: Operating System :: Microsoft :: Windows
Classifier: Programming Language :: Python
Classifier: Programming Language :: Python :: 3
Classifier: Programming Language :: Python :: 3.9
Classifier: Programming Language :: Python :: 3.10
Classifier: Programming Language :: Python :: 3.11
Classifier: Programming Language :: Python :: 3.12
Classifier: Programming Language :: Python :: Implementation :: CPython
Classifier: Topic :: Software Development :: Libraries
Classifier: Topic :: Scientific/Engineering :: Physics
Classifier: Topic :: Utilities
Requires-Python: >=3.9
License-File: LICENSE
License-File: LICENSE-AstAlg.txt
License-File: AUTHORS.rst
Requires-Dist: numpy
Provides-Extra: test
Requires-Dist: build; extra == "test"
Requires-Dist: flake8; extra == "test"
Requires-Dist: flake8-docstrings; extra == "test"
Requires-Dist: pytest; extra == "test"
Requires-Dist: pytest-cov; extra == "test"
Provides-Extra: doc
Requires-Dist: sphinx>=1.3; extra == "doc"
Requires-Dist: sphinxcontrib-napoleon; extra == "doc"
Requires-Dist: numpydoc; extra == "doc"
Requires-Dist: pyproject_parser; extra == "doc"
Requires-Dist: sphinx-rtd-theme>=1.2.2; extra == "doc"
